nonebot_plugin_steam_info-1.3.5.dist-info/METADATA
nonebot_plugin_steam_info-1.3.5.dist-info/WHEEL
nonebot_plugin_steam_info-1.3.5.dist-info/entry_points.txt
nonebot_plugin_steam_info-1.3.5.dist-info/licenses/LICENSE
nonebot_plugin_steam_info/__init__.py
nonebot_plugin_steam_info/config.py
nonebot_plugin_steam_info/data_source.py
nonebot_plugin_steam_info/draw.py
nonebot_plugin_steam_info/models.py
nonebot_plugin_steam_info/res/bg_dots.png
nonebot_plugin_steam_info/res/busy.png
nonebot_plugin_steam_info/res/default_achievement_image.png
nonebot_plugin_steam_info/res/default_header_image.jpg
nonebot_plugin_steam_info/res/friends_search.png
nonebot_plugin_steam_info/res/gaming.png
nonebot_plugin_steam_info/res/parent_status.png
nonebot_plugin_steam_info/res/unknown_avatar.jpg
nonebot_plugin_steam_info/res/zzz_gaming.png
nonebot_plugin_steam_info/res/zzz_online.png
nonebot_plugin_steam_info/steam.py
nonebot_plugin_steam_info/utils.py
nonebot_plugin_steam_info-1.3.5.dist-info/RECORD
