Metadata-Version: 2.1
Name: nonebot-plugin-steam-info
Version: 1.3.5
Summary: Steam 好友状态播报 NoneBot 插件
Author-Email: zhaomaoniu <2667292003@qq.com>
License: MIT
Requires-Python: >=3.9
Requires-Dist: nonebot2>=2.2.0
Requires-Dist: nonebot-plugin-alconna>=0.54.2
Requires-Dist: Pillow>=10.2.0
Requires-Dist: nonebot-plugin-apscheduler>=0.4.0
Requires-Dist: nonebot-plugin-localstore>=0.6.0
Requires-Dist: httpx<0.28.0,>=0.27.0
Requires-Dist: numpy>=1.24.4
Requires-Dist: beautifulsoup4>=4.12.3
Requires-Dist: pytz>=2024.2
